simgenes/__init__.py
simgenes/simgenes.py
simgenes-0.0.22.dist-info/METADATA
simgenes-0.0.22.dist-info/WHEEL
simgenes-0.0.22.dist-info/licenses/LICENSE
simgenes-0.0.22.dist-info/RECORD
