Metadata-Version: 2.1
Name: Simgenes
Version: 0.0.22
Summary: A package to generate random gene/protein sequences
Project-URL: Homepage, https://github.com/celiosantosjr/simgenes
Project-URL: Bug Tracker, https://github.com/pypa/sampleproject/issues
Author-email: "Celio D. Santos-Junior" <celio.diasjunior@gmail.com>
License-File: LICENSE
Classifier: License :: OSI Approved :: MIT License
Classifier: Operating System :: OS Independent
Classifier: Programming Language :: Python :: 3
Requires-Python: >=3.8
